dagster_gcp_pyspark/__init__.py
dagster_gcp_pyspark/py.typed
dagster_gcp_pyspark/version.py
dagster_gcp_pyspark/bigquery/__init__.py
dagster_gcp_pyspark/bigquery/bigquery_pyspark_type_handler.py
dagster_gcp_pyspark-0.28.13.dist-info/licenses/LICENSE
dagster_gcp_pyspark-0.28.13.dist-info/METADATA
dagster_gcp_pyspark-0.28.13.dist-info/WHEEL
dagster_gcp_pyspark-0.28.13.dist-info/top_level.txt
dagster_gcp_pyspark-0.28.13.dist-info/RECORD
